ellipsis/__init__.py
ellipsis/apiManager.py
ellipsis/sanitize.py
ellipsis/account/__init__.py
ellipsis/account/root.py
ellipsis/account/accessToken/__init__.py
ellipsis/account/accessToken/root.py
ellipsis/compute/__init__.py
ellipsis/compute/root.py
ellipsis/path/__init__.py
ellipsis/path/root.py
ellipsis/path/bookmark/__init__.py
ellipsis/path/bookmark/root.py
ellipsis/path/file/__init__.py
ellipsis/path/file/root.py
ellipsis/path/folder/__init__.py
ellipsis/path/folder/root.py
ellipsis/path/hashtag/__init__.py
ellipsis/path/hashtag/root.py
ellipsis/path/invite/__init__.py
ellipsis/path/invite/root.py
ellipsis/path/member/__init__.py
ellipsis/path/member/root.py
ellipsis/path/pointCloud/__init__.py
ellipsis/path/pointCloud/root.py
ellipsis/path/pointCloud/timestamp/__init__.py
ellipsis/path/pointCloud/timestamp/root.py
ellipsis/path/pointCloud/timestamp/util.py
ellipsis/path/pointCloud/timestamp/file/__init__.py
ellipsis/path/pointCloud/timestamp/file/root.py
ellipsis/path/pointCloud/timestamp/order/__init__.py
ellipsis/path/pointCloud/timestamp/order/root.py
ellipsis/path/raster/__init__.py
ellipsis/path/raster/root.py
ellipsis/path/raster/style/__init__.py
ellipsis/path/raster/style/root.py
ellipsis/path/raster/timestamp/__init__.py
ellipsis/path/raster/timestamp/root.py
ellipsis/path/raster/timestamp/util.py
ellipsis/path/raster/timestamp/file/__init__.py
ellipsis/path/raster/timestamp/file/root.py
ellipsis/path/raster/timestamp/order/__init__.py
ellipsis/path/raster/timestamp/order/root.py
ellipsis/path/setUpTask/__init__.py
ellipsis/path/setUpTask/root.py
ellipsis/path/usage/__init__.py
ellipsis/path/usage/root.py
ellipsis/path/vector/__init__.py
ellipsis/path/vector/root.py
ellipsis/path/vector/featureProperty/__init__.py
ellipsis/path/vector/featureProperty/root.py
ellipsis/path/vector/style/__init__.py
ellipsis/path/vector/style/root.py
ellipsis/path/vector/timestamp/__init__.py
ellipsis/path/vector/timestamp/root.py
ellipsis-3.3.1.dist-info/LICENSE
ellipsis-3.3.1.dist-info/METADATA
ellipsis-3.3.1.dist-info/WHEEL
ellipsis-3.3.1.dist-info/top_level.txt
ellipsis-3.3.1.dist-info/RECORD
