Metadata-Version: 2.1
Name: ellipsis
Version: 3.3.1
Summary: Package to interact with the Ellipsis API
Home-page: https://github.com/ellipsis-drive-internal/python-package
Author: Daniel van der Maas
Author-email: daniel@ellipsis-drive.com
Classifier: Programming Language :: Python :: 3
Classifier: License :: OSI Approved :: MIT License
Classifier: Operating System :: OS Independent
Requires-Python: >=3.6
License-File: LICENSE
Requires-Dist: Fiona
Requires-Dist: Pillow
Requires-Dist: Shapely
Requires-Dist: dill
Requires-Dist: geopandas
Requires-Dist: geopy
Requires-Dist: imagecodecs
Requires-Dist: imageio
Requires-Dist: matplotlib
Requires-Dist: numpy
Requires-Dist: pandas
Requires-Dist: pygltflib
Requires-Dist: pyproj
Requires-Dist: rasterio
Requires-Dist: requests
Requires-Dist: requests-toolbelt
Requires-Dist: scikit-image
Requires-Dist: tifffile
